yaqc_qtpy/VERSION
yaqc_qtpy/__init__.py
yaqc_qtpy/__main__.py
yaqc_qtpy/__version__.py
yaqc_qtpy/_config_widget.py
yaqc_qtpy/_dotdict.py
yaqc_qtpy/_has_position_widget.py
yaqc_qtpy/_is_sensor_widget.py
yaqc_qtpy/_lru_dict.py
yaqc_qtpy/_main_widget.py
yaqc_qtpy/_main_window.py
yaqc_qtpy/_plot.py
yaqc_qtpy/_qclient.py
yaqc_qtpy/_qproperty.py
yaqc_qtpy/_qthread.py
yaqc_qtpy/_splash.py
yaqc_qtpy/qtype_items.py
yaqc_qtpy/property_items/__init__.py
yaqc_qtpy/property_items/_boolean.py
yaqc_qtpy/property_items/_disconnect.py
yaqc_qtpy/property_items/_enum.py
yaqc_qtpy/property_items/_float.py
yaqc_qtpy/property_items/_integer.py
yaqc_qtpy/property_items/_string.py
yaqc_qtpy/splash-images/000.jpg
yaqc_qtpy/splash-images/001.jpg
yaqc_qtpy/splash-images/002.jpg
yaqc_qtpy/splash-images/003.jpg
yaqc_qtpy/splash-images/004.jpg
yaqc_qtpy/splash-images/LICENSE
yaqc_qtpy-2022.6.0.dist-info/entry_points.txt
yaqc_qtpy-2022.6.0.dist-info/LICENSE
yaqc_qtpy-2022.6.0.dist-info/WHEEL
yaqc_qtpy-2022.6.0.dist-info/METADATA
yaqc_qtpy-2022.6.0.dist-info/RECORD
