Metadata-Version: 2.1
Name: yaqc-qtpy
Version: 2022.6.0
Summary: Tooling for building simple yaq clients using qtpy.
Home-page: https://yaq.fyi
Author: Blaise Thompson
Author-email: blaise@untzag.com
Requires-Python: >=3.7
Classifier: Development Status :: 2 - Pre-Alpha
Classifier: Intended Audience :: Science/Research
Classifier: License :: OSI Approved :: GNU Lesser General Public License v3 (LGPLv3)
Classifier: Natural Language :: English
Classifier: Programming Language :: Python :: 3
Classifier: Programming Language :: Python :: 3.7
Classifier: Programming Language :: Python :: 3.8
Classifier: Topic :: Scientific/Engineering
Requires-Dist: yaqd-core>=2020.06.3
Requires-Dist: yaqc
Requires-Dist: yaq-traits
Requires-Dist: yaqd-control
Requires-Dist: click
Requires-Dist: qtpy
Requires-Dist: qtypes>=2022.6.0
Requires-Dist: pyqtgraph
Requires-Dist: pyside2
Requires-Dist: numpy
Requires-Dist: qtconsole
Requires-Dist: black ; extra == "dev"
Requires-Dist: pre-commit ; extra == "dev"
Project-URL: Issues, https://github.com/yaq-project/yaqc-qtpy/issues
Project-URL: Source, https://github.com/yaq-project/yaqc-qtpy
Provides-Extra: dev
